setup.py
brynq_sdk_vplan/__init__.py
brynq_sdk_vplan/activity.py
brynq_sdk_vplan/get_data.py
brynq_sdk_vplan/item.py
brynq_sdk_vplan/leave.py
brynq_sdk_vplan/order.py
brynq_sdk_vplan/project.py
brynq_sdk_vplan/resource.py
brynq_sdk_vplan/time_tracking.py
brynq_sdk_vplan/user.py
brynq_sdk_vplan.egg-info/PKG-INFO
brynq_sdk_vplan.egg-info/SOURCES.txt
brynq_sdk_vplan.egg-info/dependency_links.txt
brynq_sdk_vplan.egg-info/not-zip-safe
brynq_sdk_vplan.egg-info/requires.txt
brynq_sdk_vplan.egg-info/top_level.txt