Metadata-Version: 1.0
Name: brynq-sdk-vplan
Version: 1.2.4
Summary: vPlan wrapper from BrynQ
Home-page: UNKNOWN
Author: BrynQ
Author-email: support@brynq.com
License: BrynQ License
Platform: UNKNOWN
